CONTRIBUTING.md
Jenkinsfile
MANIFEST.in
README.rst
setup.py
buildouts/plone4/buildout.cfg
buildouts/plone4/install.sh
buildouts/plone4/versions.cfg
buildouts/plone40/deployment.cfg
buildouts/plone40/devel.cfg
buildouts/plone40/hudson.cfg
buildouts/plone40/i18nize.in
buildouts/plone40/install.sh
buildouts/plone40/versions.cfg
buildouts/plone41/deployment.cfg
buildouts/plone41/devel.cfg
buildouts/plone41/hudson.cfg
buildouts/plone41/i18nize.in
buildouts/plone41/install.sh
buildouts/plone41/versions.cfg
docs/HISTORY.txt
docs/LICENSE.GPL
docs/LICENSE.txt
eea/__init__.py
eea.tags.egg-info/PKG-INFO
eea.tags.egg-info/SOURCES.txt
eea.tags.egg-info/dependency_links.txt
eea.tags.egg-info/entry_points.txt
eea.tags.egg-info/namespace_packages.txt
eea.tags.egg-info/not-zip-safe
eea.tags.egg-info/requires.txt
eea.tags.egg-info/top_level.txt
eea/tags/__init__.py
eea/tags/configure.zcml
eea/tags/profiles.zcml
eea/tags/version.txt
eea/tags/browser/__init__.py
eea/tags/browser/configure.zcml
eea/tags/browser/interfaces.py
eea/tags/browser/tags.py
eea/tags/browser/css/tags.css
eea/tags/browser/js/tags.js
eea/tags/locales/eea.pot
eea/tags/locales/update.sh
eea/tags/locales/bg/LC_MESSAGES/eea.po
eea/tags/locales/cs/LC_MESSAGES/eea.po
eea/tags/locales/da/LC_MESSAGES/eea.po
eea/tags/locales/de/LC_MESSAGES/eea.po
eea/tags/locales/el/LC_MESSAGES/eea.po
eea/tags/locales/en/LC_MESSAGES/eea.po
eea/tags/locales/es/LC_MESSAGES/eea.po
eea/tags/locales/et/LC_MESSAGES/eea.po
eea/tags/locales/eu/LC_MESSAGES/eea.po
eea/tags/locales/fi/LC_MESSAGES/eea.po
eea/tags/locales/fr/LC_MESSAGES/eea.po
eea/tags/locales/hu/LC_MESSAGES/eea.po
eea/tags/locales/is/LC_MESSAGES/eea.po
eea/tags/locales/it/LC_MESSAGES/eea.po
eea/tags/locales/kl/LC_MESSAGES/eea.po
eea/tags/locales/lt/LC_MESSAGES/eea.po
eea/tags/locales/lv/LC_MESSAGES/eea.po
eea/tags/locales/mt/LC_MESSAGES/eea.po
eea/tags/locales/nl/LC_MESSAGES/eea.po
eea/tags/locales/no/LC_MESSAGES/eea.po
eea/tags/locales/pl/LC_MESSAGES/eea.po
eea/tags/locales/pt/LC_MESSAGES/eea.po
eea/tags/locales/ro/LC_MESSAGES/eea.po
eea/tags/locales/ru/LC_MESSAGES/eea.po
eea/tags/locales/sk/LC_MESSAGES/eea.po
eea/tags/locales/sl/LC_MESSAGES/eea.po
eea/tags/locales/sv/LC_MESSAGES/eea.po
eea/tags/locales/tr/LC_MESSAGES/eea.po
